[
	{
		"id": "unauthorized-action",
		"description": "Agent took an action the user did not direct",
		"severity": "error",
		"category": "unauthorized",
		"source": "bundled"
	},
	{
		"id": "destructive-without-confirmation",
		"description": "Destructive operation executed without explicit user confirmation",
		"severity": "error",
		"category": "unauthorized",
		"source": "project"
	},
	{
		"id": "protected-surface-without-authorization",
		"description": "Write attempted on protected surfaces without explicit authorization",
		"severity": "error",
		"category": "unauthorized",
		"source": "project"
	},
	{
		"id": "scope-expansion-without-ask",
		"description": "Agent expanded task scope to unrelated packages/files without asking",
		"severity": "warning",
		"category": "scope",
		"source": "project"
	}
]
